README.md
rqalpha_mod_faithquant/__init__.py
rqalpha_mod_faithquant/mod.py
rqalpha_mod_faithquant-0.0.1.dist-info/METADATA
rqalpha_mod_faithquant-0.0.1.dist-info/WHEEL
rqalpha_mod_faithquant-0.0.1.dist-info/RECORD
