Metadata-Version: 2.1
Name: rqalpha-mod-faithquant
Version: 0.0.1
Summary: RQAlpha Mod FaithQuant
Keywords: faithquant,fqdatac,datavita,fatbulls,fatbull,fqprism
Author: Jeffrey
Author-email: wangjiangfeng@hcyjs.com
Requires-Python: >=3.10,<4.0
Classifier: Programming Language :: Python :: 3
Classifier: Programming Language :: Python :: 3.10
Classifier: Programming Language :: Python :: 3.11
Requires-Dist: rqalpha (>=5.2,<6.0)
